llamacpp_client/__init__.py
llamacpp_client/llamacpp_client.py
llamacpp_client-0.1.3.dist-info/METADATA
llamacpp_client-0.1.3.dist-info/WHEEL
llamacpp_client-0.1.3.dist-info/top_level.txt
llamacpp_client-0.1.3.dist-info/RECORD
