Metadata-Version: 2.4
Name: llamacpp-client
Version: 0.1.3
Summary: Client for LlamaCpp HTTP Server
Author-email: Luís Gomes <lmdgomes@fc.ul.pt>
Requires-Python: >=3.9
Requires-Dist: httpx
Requires-Dist: requests
